{
  "iterations": 100000,
  "comment": "After Tour 3 Ends",
  "team_outcomes": {
    "Team Liquid": {
      "1st": 19689,
      "2nd": 15002,
      "3rd": 10322,
      "4th": 7419,
      "5-6th": 10161,
      "7-8th": 3896,
      "9-12th": 4288,
      "13-16th": 4295,
      "17-18th": 575,
      "19-20th": 0,
      "elim_wc": 0,
      "points_qual": 100000,
      "reg_qual": 0,
      "wc_qual": 0
    },
    "Shopify Rebellion": {
      "1st": 8422,
      "2nd": 9830,
      "3rd": 9373,
      "4th": 8304,
      "5-6th": 13567,
      "7-8th": 7922,
      "9-12th": 10070,
      "13-16th": 10057,
      "17-18th": 1669,
      "19-20th": 0,
      "elim_wc": 0,
      "points_qual": 100000,
      "reg_qual": 0,
      "wc_qual": 0
    },
    "Tundra Esports": {
      "1st": 19275,
      "2nd": 14555,
      "3rd": 10446,
      "4th": 7501,
      "5-6th": 10230,
      "7-8th": 3920,
      "9-12th": 4360,
      "13-16th": 4279,
      "17-18th": 572,
      "19-20th": 0,
      "elim_wc": 0,
      "points_qual": 100000,
      "reg_qual": 0,
      "wc_qual": 0
    },
    "Gaimin Gladiators": {
      "1st": 23804,
      "2nd": 15702,
      "3rd": 10016,
      "4th": 6916,
      "5-6th": 9024,
      "7-8th": 3146,
      "9-12th": 3401,
      "13-16th": 3383,
      "17-18th": 370,
      "19-20th": 0,
      "elim_wc": 0,
      "points_qual": 100000,
      "reg_qual": 0,
      "wc_qual": 0
    },
    "beastcoast": {
      "1st": 852,
      "2nd": 1998,
      "3rd": 3508,
      "4th": 4900,
      "5-6th": 12354,
      "7-8th": 15636,
      "9-12th": 29809,
      "13-16th": 29824,
      "17-18th": 9629,
      "19-20th": 0,
      "elim_wc": 0,
      "points_qual": 98397,
      "reg_qual": 922,
      "wc_qual": 0
    },
    "Evil Geniuses": {
      "1st": 3368,
      "2nd": 5515,
      "3rd": 6862,
      "4th": 7324,
      "5-6th": 14371,
      "7-8th": 12049,
      "9-12th": 18154,
      "13-16th": 18055,
      "17-18th": 4006,
      "19-20th": 0,
      "elim_wc": 0,
      "points_qual": 100000,
      "reg_qual": 0,
      "wc_qual": 0
    },
    "PSG.LGD": {
      "1st": 7951,
      "2nd": 8700,
      "3rd": 8496,
      "4th": 7343,
      "5-6th": 11775,
      "7-8th": 6788,
      "9-12th": 8422,
      "13-16th": 8542,
      "17-18th": 1389,
      "19-20th": 0,
      "elim_wc": 0,
      "points_qual": 78539,
      "reg_qual": 9266,
      "wc_qual": 0
    },
    "BetBoom Team": {
      "1st": 1058,
      "2nd": 2164,
      "3rd": 3262,
      "4th": 4332,
      "5-6th": 9714,
      "7-8th": 10565,
      "9-12th": 18023,
      "13-16th": 18078,
      "17-18th": 5011,
      "19-20th": 0,
      "elim_wc": 0,
      "points_qual": 48436,
      "reg_qual": 22948,
      "wc_qual": 0
    },
    "Talon": {
      "1st": 1745,
      "2nd": 3505,
      "3rd": 5172,
      "4th": 6247,
      "5-6th": 13917,
      "7-8th": 14288,
      "9-12th": 23945,
      "13-16th": 24086,
      "17-18th": 6184,
      "19-20th": 0,
      "elim_wc": 0,
      "points_qual": 100000,
      "reg_qual": 0,
      "wc_qual": 0
    },
    "9Pandas": {
      "1st": 2120,
      "2nd": 3847,
      "3rd": 5529,
      "4th": 6553,
      "5-6th": 14490,
      "7-8th": 13779,
      "9-12th": 22305,
      "13-16th": 22265,
      "17-18th": 5589,
      "19-20th": 0,
      "elim_wc": 0,
      "points_qual": 99989,
      "reg_qual": 5,
      "wc_qual": 0
    },
    "Team Spirit": {
      "1st": 4961,
      "2nd": 7024,
      "3rd": 8065,
      "4th": 7871,
      "5-6th": 14211,
      "7-8th": 10409,
      "9-12th": 14604,
      "13-16th": 14417,
      "17-18th": 2855,
      "19-20th": 0,
      "elim_wc": 0,
      "points_qual": 99800,
      "reg_qual": 123,
      "wc_qual": 0
    },
    "TSM": {
      "1st": 380,
      "2nd": 980,
      "3rd": 2113,
      "4th": 3334,
      "5-6th": 9667,
      "7-8th": 14375,
      "9-12th": 30891,
      "13-16th": 31098,
      "17-18th": 11834,
      "19-20th": 0,
      "elim_wc": 0,
      "points_qual": 74246,
      "reg_qual": 14294,
      "wc_qual": 0
    },
    "HYDRA": {
      "1st": 3,
      "2nd": 13,
      "3rd": 46,
      "4th": 80,
      "5-6th": 472,
      "7-8th": 1138,
      "9-12th": 4224,
      "13-16th": 4185,
      "17-18th": 3268,
      "19-20th": 0,
      "elim_wc": 0,
      "points_qual": 0,
      "reg_qual": 9857,
      "wc_qual": 0
    },
    "Quest Esports": {
      "1st": 636,
      "2nd": 1129,
      "3rd": 1583,
      "4th": 1736,
      "5-6th": 3721,
      "7-8th": 3693,
      "9-12th": 5938,
      "13-16th": 5973,
      "17-18th": 1431,
      "19-20th": 0,
      "elim_wc": 0,
      "points_qual": 633,
      "reg_qual": 26368,
      "wc_qual": 0
    },
    "Mad Kings Esports": {
      "1st": 0,
      "2nd": 2,
      "3rd": 10,
      "4th": 33,
      "5-6th": 194,
      "7-8th": 813,
      "9-12th": 3952,
      "13-16th": 3952,
      "17-18th": 5674,
      "19-20th": 0,
      "elim_wc": 0,
      "points_qual": 0,
      "reg_qual": 10941,
      "wc_qual": 0
    },
    "DogChamp": {
      "1st": 0,
      "2nd": 0,
      "3rd": 2,
      "4th": 12,
      "5-6th": 99,
      "7-8th": 448,
      "9-12th": 2929,
      "13-16th": 2931,
      "17-18th": 5518,
      "19-20th": 0,
      "elim_wc": 0,
      "points_qual": 0,
      "reg_qual": 9112,
      "wc_qual": 0
    },
    "BLEED": {
      "1st": 36,
      "2nd": 113,
      "3rd": 323,
      "4th": 595,
      "5-6th": 2046,
      "7-8th": 4229,
      "9-12th": 10601,
      "13-16th": 10746,
      "17-18th": 5863,
      "19-20th": 0,
      "elim_wc": 0,
      "points_qual": 8404,
      "reg_qual": 18515,
      "wc_qual": 0
    },
    "Azure Ray": {
      "1st": 81,
      "2nd": 184,
      "3rd": 342,
      "4th": 569,
      "5-6th": 1533,
      "7-8th": 2146,
      "9-12th": 4638,
      "13-16th": 4548,
      "17-18th": 1733,
      "19-20th": 0,
      "elim_wc": 0,
      "points_qual": 0,
      "reg_qual": 13643,
      "wc_qual": 0
    },
    "Execration": {
      "1st": 189,
      "2nd": 436,
      "3rd": 988,
      "4th": 1654,
      "5-6th": 4923,
      "7-8th": 7883,
      "9-12th": 18213,
      "13-16th": 18214,
      "17-18th": 7781,
      "19-20th": 0,
      "elim_wc": 0,
      "points_qual": 29510,
      "reg_qual": 19901,
      "wc_qual": 0
    },
    "One Move": {
      "1st": 4,
      "2nd": 15,
      "3rd": 65,
      "4th": 133,
      "5-6th": 502,
      "7-8th": 1449,
      "9-12th": 4962,
      "13-16th": 4877,
      "17-18th": 3806,
      "19-20th": 0,
      "elim_wc": 0,
      "points_qual": 0,
      "reg_qual": 11675,
      "wc_qual": 0
    },
    "OG": {
      "1st": 1621,
      "2nd": 2329,
      "3rd": 2729,
      "4th": 2881,
      "5-6th": 5232,
      "7-8th": 4196,
      "9-12th": 6077,
      "13-16th": 6090,
      "17-18th": 1226,
      "19-20th": 0,
      "elim_wc": 0,
      "points_qual": 0,
      "reg_qual": 36962,
      "wc_qual": 0
    },
    "Thunder Awaken": {
      "1st": 44,
      "2nd": 182,
      "3rd": 451,
      "4th": 917,
      "5-6th": 3297,
      "7-8th": 6784,
      "9-12th": 19195,
      "13-16th": 19116,
      "17-18th": 12636,
      "19-20th": 0,
      "elim_wc": 0,
      "points_qual": 0,
      "reg_qual": 48211,
      "wc_qual": 0
    },
    "nouns": {
      "1st": 107,
      "2nd": 334,
      "3rd": 773,
      "4th": 1588,
      "5-6th": 5013,
      "7-8th": 9477,
      "9-12th": 25035,
      "13-16th": 24989,
      "17-18th": 13280,
      "19-20th": 0,
      "elim_wc": 0,
      "points_qual": 13094,
      "reg_qual": 49962,
      "wc_qual": 0
    },
    "Team SMG": {
      "1st": 5,
      "2nd": 42,
      "3rd": 115,
      "4th": 245,
      "5-6th": 874,
      "7-8th": 1950,
      "9-12th": 5592,
      "13-16th": 5590,
      "17-18th": 3450,
      "19-20th": 0,
      "elim_wc": 0,
      "points_qual": 0,
      "reg_qual": 13549,
      "wc_qual": 0
    },
    "Team Aster": {
      "1st": 2353,
      "2nd": 3540,
      "3rd": 4675,
      "4th": 4583,
      "5-6th": 9374,
      "7-8th": 7618,
      "9-12th": 11672,
      "13-16th": 11622,
      "17-18th": 2591,
      "19-20th": 0,
      "elim_wc": 0,
      "points_qual": 47654,
      "reg_qual": 16806,
      "wc_qual": 0
    },
    "Natus Vincere": {
      "1st": 0,
      "2nd": 3,
      "3rd": 11,
      "4th": 36,
      "5-6th": 180,
      "7-8th": 499,
      "9-12th": 2093,
      "13-16th": 2042,
      "17-18th": 1939,
      "19-20th": 0,
      "elim_wc": 0,
      "points_qual": 0,
      "reg_qual": 4987,
      "wc_qual": 0
    },
    "Team Secret": {
      "1st": 82,
      "2nd": 203,
      "3rd": 400,
      "4th": 533,
      "5-6th": 1461,
      "7-8th": 1990,
      "9-12th": 4020,
      "13-16th": 3979,
      "17-18th": 1335,
      "19-20th": 0,
      "elim_wc": 0,
      "points_qual": 0,
      "reg_qual": 12450,
      "wc_qual": 0
    },
    "Army Geniuses Mansion": {
      "1st": 2,
      "2nd": 10,
      "3rd": 38,
      "4th": 91,
      "5-6th": 343,
      "7-8th": 974,
      "9-12th": 3403,
      "13-16th": 3383,
      "17-18th": 2527,
      "19-20th": 0,
      "elim_wc": 0,
      "points_qual": 0,
      "reg_qual": 7851,
      "wc_qual": 0
    },
    "Xtreme Gaming": {
      "1st": 777,
      "2nd": 1322,
      "3rd": 1785,
      "4th": 2193,
      "5-6th": 4603,
      "7-8th": 4337,
      "9-12th": 6909,
      "13-16th": 6906,
      "17-18th": 1686,
      "19-20th": 0,
      "elim_wc": 0,
      "points_qual": 0,
      "reg_qual": 32153,
      "wc_qual": 0
    },
    "Hokori": {
      "1st": 0,
      "2nd": 4,
      "3rd": 15,
      "4th": 73,
      "5-6th": 347,
      "7-8th": 1299,
      "9-12th": 5835,
      "13-16th": 5848,
      "17-18th": 7408,
      "19-20th": 0,
      "elim_wc": 0,
      "points_qual": 0,
      "reg_qual": 15433,
      "wc_qual": 0
    },
    "felt": {
      "1st": 0,
      "2nd": 0,
      "3rd": 0,
      "4th": 2,
      "5-6th": 18,
      "7-8th": 136,
      "9-12th": 1212,
      "13-16th": 1206,
      "17-18th": 4157,
      "19-20th": 0,
      "elim_wc": 0,
      "points_qual": 0,
      "reg_qual": 5536,
      "wc_qual": 0
    },
    "BOOM Esports": {
      "1st": 8,
      "2nd": 46,
      "3rd": 80,
      "4th": 189,
      "5-6th": 794,
      "7-8th": 1648,
      "9-12th": 4881,
      "13-16th": 4902,
      "17-18th": 2958,
      "19-20th": 0,
      "elim_wc": 0,
      "points_qual": 0,
      "reg_qual": 11719,
      "wc_qual": 0
    },
    "Vici Gaming": {
      "1st": 15,
      "2nd": 38,
      "3rd": 100,
      "4th": 173,
      "5-6th": 545,
      "7-8th": 971,
      "9-12th": 2257,
      "13-16th": 2246,
      "17-18th": 1000,
      "19-20th": 0,
      "elim_wc": 0,
      "points_qual": 0,
      "reg_qual": 5901,
      "wc_qual": 0
    },
    "Virtus.pro": {
      "1st": 120,
      "2nd": 452,
      "3rd": 802,
      "4th": 1293,
      "5-6th": 3524,
      "7-8th": 5469,
      "9-12th": 11571,
      "13-16th": 11859,
      "17-18th": 4616,
      "19-20th": 0,
      "elim_wc": 0,
      "points_qual": 0,
      "reg_qual": 33532,
      "wc_qual": 0
    },
    "B8": {
      "1st": 0,
      "2nd": 1,
      "3rd": 0,
      "4th": 6,
      "5-6th": 27,
      "7-8th": 178,
      "9-12th": 1454,
      "13-16th": 1465,
      "17-18th": 4142,
      "19-20th": 0,
      "elim_wc": 0,
      "points_qual": 0,
      "reg_qual": 5833,
      "wc_qual": 0
    },
    "Entity": {
      "1st": 130,
      "2nd": 356,
      "3rd": 615,
      "4th": 799,
      "5-6th": 1966,
      "7-8th": 2369,
      "9-12th": 4606,
      "13-16th": 4559,
      "17-18th": 1469,
      "19-20th": 0,
      "elim_wc": 0,
      "points_qual": 0,
      "reg_qual": 15687,
      "wc_qual": 0
    },
    "Team Sexy": {
      "1st": 1,
      "2nd": 1,
      "3rd": 4,
      "4th": 13,
      "5-6th": 98,
      "7-8th": 297,
      "9-12th": 1411,
      "13-16th": 1366,
      "17-18th": 1573,
      "19-20th": 0,
      "elim_wc": 0,
      "points_qual": 0,
      "reg_qual": 3523,
      "wc_qual": 0
    },
    "Aster.Aries": {
      "1st": 0,
      "2nd": 3,
      "3rd": 8,
      "4th": 13,
      "5-6th": 92,
      "7-8th": 233,
      "9-12th": 780,
      "13-16th": 786,
      "17-18th": 648,
      "19-20th": 0,
      "elim_wc": 0,
      "points_qual": 0,
      "reg_qual": 1874,
      "wc_qual": 0
    },
    "Geek Slate": {
      "1st": 0,
      "2nd": 1,
      "3rd": 4,
      "4th": 6,
      "5-6th": 68,
      "7-8th": 245,
      "9-12th": 1171,
      "13-16th": 1163,
      "17-18th": 1410,
      "19-20th": 0,
      "elim_wc": 0,
      "points_qual": 0,
      "reg_qual": 2986,
      "wc_qual": 0
    },
    "Nemiga Gaming": {
      "1st": 6,
      "2nd": 18,
      "3rd": 44,
      "4th": 116,
      "5-6th": 526,
      "7-8th": 1359,
      "9-12th": 4337,
      "13-16th": 4334,
      "17-18th": 3029,
      "19-20th": 0,
      "elim_wc": 0,
      "points_qual": 0,
      "reg_qual": 10184,
      "wc_qual": 0
    },
    "Infinity": {
      "1st": 0,
      "2nd": 0,
      "3rd": 0,
      "4th": 5,
      "5-6th": 54,
      "7-8th": 343,
      "9-12th": 2473,
      "13-16th": 2455,
      "17-18th": 5288,
      "19-20th": 0,
      "elim_wc": 0,
      "points_qual": 0,
      "reg_qual": 8229,
      "wc_qual": 0
    },
    "Blacklist Rivalry": {
      "1st": 12,
      "2nd": 50,
      "3rd": 172,
      "4th": 330,
      "5-6th": 1225,
      "7-8th": 2678,
      "9-12th": 7376,
      "13-16th": 7469,
      "17-18th": 4352,
      "19-20th": 0,
      "elim_wc": 0,
      "points_qual": 1298,
      "reg_qual": 16679,
      "wc_qual": 0
    },
    "Lava Esports": {
      "1st": 0,
      "2nd": 0,
      "3rd": 0,
      "4th": 0,
      "5-6th": 12,
      "7-8th": 100,
      "9-12th": 740,
      "13-16th": 735,
      "17-18th": 1950,
      "19-20th": 0,
      "elim_wc": 0,
      "points_qual": 0,
      "reg_qual": 2822,
      "wc_qual": 0
    },
    "INVICTUS GAMING": {
      "1st": 135,
      "2nd": 330,
      "3rd": 557,
      "4th": 845,
      "5-6th": 2188,
      "7-8th": 2744,
      "9-12th": 5323,
      "13-16th": 5341,
      "17-18th": 1762,
      "19-20th": 0,
      "elim_wc": 0,
      "points_qual": 0,
      "reg_qual": 17406,
      "wc_qual": 0
    },
    "Vivo Keyd Stars": {
      "1st": 0,
      "2nd": 0,
      "3rd": 0,
      "4th": 1,
      "5-6th": 10,
      "7-8th": 88,
      "9-12th": 639,
      "13-16th": 640,
      "17-18th": 1978,
      "19-20th": 0,
      "elim_wc": 0,
      "points_qual": 0,
      "reg_qual": 2728,
      "wc_qual": 0
    },
    "5RATFORCESTAFF": {
      "1st": 0,
      "2nd": 0,
      "3rd": 7,
      "4th": 9,
      "5-6th": 156,
      "7-8th": 628,
      "9-12th": 3932,
      "13-16th": 3847,
      "17-18th": 6394,
      "19-20th": 0,
      "elim_wc": 0,
      "points_qual": 0,
      "reg_qual": 11313,
      "wc_qual": 0
    },
    "Balrogs  Esports\u2122": {
      "1st": 0,
      "2nd": 0,
      "3rd": 0,
      "4th": 0,
      "5-6th": 10,
      "7-8th": 67,
      "9-12th": 551,
      "13-16th": 551,
      "17-18th": 1685,
      "19-20th": 0,
      "elim_wc": 0,
      "points_qual": 0,
      "reg_qual": 2321,
      "wc_qual": 0
    },
    "na Div 2 team #2": {
      "1st": 0,
      "2nd": 0,
      "3rd": 0,
      "4th": 1,
      "5-6th": 0,
      "7-8th": 9,
      "9-12th": 141,
      "13-16th": 138,
      "17-18th": 769,
      "19-20th": 0,
      "elim_wc": 0,
      "points_qual": 0,
      "reg_qual": 922,
      "wc_qual": 0
    },
    "Qhali": {
      "1st": 0,
      "2nd": 0,
      "3rd": 0,
      "4th": 0,
      "5-6th": 2,
      "7-8th": 25,
      "9-12th": 214,
      "13-16th": 219,
      "17-18th": 793,
      "19-20th": 0,
      "elim_wc": 0,
      "points_qual": 0,
      "reg_qual": 1035,
      "wc_qual": 0
    },
    "Wildcard": {
      "1st": 0,
      "2nd": 0,
      "3rd": 0,
      "4th": 0,
      "5-6th": 0,
      "7-8th": 6,
      "9-12th": 110,
      "13-16th": 106,
      "17-18th": 601,
      "19-20th": 0,
      "elim_wc": 0,
      "points_qual": 0,
      "reg_qual": 717,
      "wc_qual": 0
    },
    "ALPHA": {
      "1st": 0,
      "2nd": 0,
      "3rd": 0,
      "4th": 0,
      "5-6th": 0,
      "7-8th": 8,
      "9-12th": 111,
      "13-16th": 111,
      "17-18th": 738,
      "19-20th": 0,
      "elim_wc": 0,
      "points_qual": 0,
      "reg_qual": 857,
      "wc_qual": 0
    },
    "Monaspa": {
      "1st": 1,
      "2nd": 4,
      "3rd": 9,
      "4th": 21,
      "5-6th": 124,
      "7-8th": 260,
      "9-12th": 842,
      "13-16th": 811,
      "17-18th": 508,
      "19-20th": 0,
      "elim_wc": 0,
      "points_qual": 0,
      "reg_qual": 1940,
      "wc_qual": 0
    },
    "IHC Esports": {
      "1st": 0,
      "2nd": 0,
      "3rd": 0,
      "4th": 0,
      "5-6th": 5,
      "7-8th": 29,
      "9-12th": 218,
      "13-16th": 207,
      "17-18th": 378,
      "19-20th": 0,
      "elim_wc": 0,
      "points_qual": 0,
      "reg_qual": 635,
      "wc_qual": 0
    },
    "sa Div 2 team #2": {
      "1st": 0,
      "2nd": 0,
      "3rd": 0,
      "4th": 0,
      "5-6th": 0,
      "7-8th": 9,
      "9-12th": 54,
      "13-16th": 58,
      "17-18th": 320,
      "19-20th": 0,
      "elim_wc": 0,
      "points_qual": 0,
      "reg_qual": 383,
      "wc_qual": 0
    },
    "Infamous Gaming": {
      "1st": 0,
      "2nd": 0,
      "3rd": 3,
      "4th": 8,
      "5-6th": 46,
      "7-8th": 208,
      "9-12th": 1489,
      "13-16th": 1461,
      "17-18th": 3166,
      "19-20th": 0,
      "elim_wc": 0,
      "points_qual": 0,
      "reg_qual": 4966,
      "wc_qual": 0
    },
    "Polaris Esports": {
      "1st": 0,
      "2nd": 0,
      "3rd": 3,
      "4th": 6,
      "5-6th": 47,
      "7-8th": 180,
      "9-12th": 818,
      "13-16th": 831,
      "17-18th": 1106,
      "19-20th": 0,
      "elim_wc": 0,
      "points_qual": 0,
      "reg_qual": 2220,
      "wc_qual": 0
    },
    "Nigma Galaxy": {
      "1st": 6,
      "2nd": 10,
      "3rd": 42,
      "4th": 82,
      "5-6th": 287,
      "7-8th": 486,
      "9-12th": 1331,
      "13-16th": 1310,
      "17-18th": 684,
      "19-20th": 0,
      "elim_wc": 0,
      "points_qual": 0,
      "reg_qual": 3299,
      "wc_qual": 0
    },
    "D1 Hustlers": {
      "1st": 0,
      "2nd": 3,
      "3rd": 10,
      "4th": 25,
      "5-6th": 115,
      "7-8th": 284,
      "9-12th": 837,
      "13-16th": 861,
      "17-18th": 594,
      "19-20th": 0,
      "elim_wc": 0,
      "points_qual": 0,
      "reg_qual": 2019,
      "wc_qual": 0
    },
    "Alliance": {
      "1st": 0,
      "2nd": 2,
      "3rd": 1,
      "4th": 6,
      "5-6th": 42,
      "7-8th": 102,
      "9-12th": 395,
      "13-16th": 394,
      "17-18th": 306,
      "19-20th": 0,
      "elim_wc": 0,
      "points_qual": 0,
      "reg_qual": 894,
      "wc_qual": 0
    },
    "Vision": {
      "1st": 0,
      "2nd": 1,
      "3rd": 13,
      "4th": 24,
      "5-6th": 138,
      "7-8th": 462,
      "9-12th": 1634,
      "13-16th": 1652,
      "17-18th": 1489,
      "19-20th": 0,
      "elim_wc": 0,
      "points_qual": 0,
      "reg_qual": 3937,
      "wc_qual": 0
    },
    "Xerxia": {
      "1st": 0,
      "2nd": 0,
      "3rd": 0,
      "4th": 4,
      "5-6th": 33,
      "7-8th": 111,
      "9-12th": 558,
      "13-16th": 572,
      "17-18th": 769,
      "19-20th": 0,
      "elim_wc": 0,
      "points_qual": 0,
      "reg_qual": 1499,
      "wc_qual": 0
    },
    "x5 Gaming": {
      "1st": 0,
      "2nd": 0,
      "3rd": 0,
      "4th": 0,
      "5-6th": 0,
      "7-8th": 2,
      "9-12th": 25,
      "13-16th": 25,
      "17-18th": 177,
      "19-20th": 0,
      "elim_wc": 0,
      "points_qual": 0,
      "reg_qual": 204,
      "wc_qual": 0
    },
    "Piggy Killer": {
      "1st": 1,
      "2nd": 0,
      "3rd": 8,
      "4th": 25,
      "5-6th": 106,
      "7-8th": 277,
      "9-12th": 891,
      "13-16th": 904,
      "17-18th": 739,
      "19-20th": 0,
      "elim_wc": 0,
      "points_qual": 0,
      "reg_qual": 2187,
      "wc_qual": 0
    },
    "SAND KING G\u00d3MEZ": {
      "1st": 0,
      "2nd": 0,
      "3rd": 0,
      "4th": 0,
      "5-6th": 1,
      "7-8th": 4,
      "9-12th": 71,
      "13-16th": 73,
      "17-18th": 449,
      "19-20th": 0,
      "elim_wc": 0,
      "points_qual": 0,
      "reg_qual": 526,
      "wc_qual": 0
    },
    "Noping VPN": {
      "1st": 0,
      "2nd": 0,
      "3rd": 0,
      "4th": 0,
      "5-6th": 0,
      "7-8th": 18,
      "9-12th": 157,
      "13-16th": 158,
      "17-18th": 757,
      "19-20th": 0,
      "elim_wc": 0,
      "points_qual": 0,
      "reg_qual": 934,
      "wc_qual": 0
    },
    "sa Div 2 team #1": {
      "1st": 0,
      "2nd": 0,
      "3rd": 0,
      "4th": 0,
      "5-6th": 0,
      "7-8th": 2,
      "9-12th": 37,
      "13-16th": 35,
      "17-18th": 216,
      "19-20th": 0,
      "elim_wc": 0,
      "points_qual": 0,
      "reg_qual": 255,
      "wc_qual": 0
    },
    "Moneymakers": {
      "1st": 0,
      "2nd": 0,
      "3rd": 0,
      "4th": 0,
      "5-6th": 11,
      "7-8th": 47,
      "9-12th": 237,
      "13-16th": 250,
      "17-18th": 548,
      "19-20th": 0,
      "elim_wc": 0,
      "points_qual": 0,
      "reg_qual": 851,
      "wc_qual": 0
    },
    "ITB.Shuffle": {
      "1st": 0,
      "2nd": 1,
      "3rd": 0,
      "4th": 0,
      "5-6th": 6,
      "7-8th": 15,
      "9-12th": 83,
      "13-16th": 85,
      "17-18th": 84,
      "19-20th": 0,
      "elim_wc": 0,
      "points_qual": 0,
      "reg_qual": 192,
      "wc_qual": 0
    },
    "noMERCY": {
      "1st": 0,
      "2nd": 0,
      "3rd": 0,
      "4th": 0,
      "5-6th": 0,
      "7-8th": 9,
      "9-12th": 118,
      "13-16th": 113,
      "17-18th": 486,
      "19-20th": 0,
      "elim_wc": 0,
      "points_qual": 0,
      "reg_qual": 616,
      "wc_qual": 0
    },
    "Ancient Tribe": {
      "1st": 0,
      "2nd": 0,
      "3rd": 1,
      "4th": 0,
      "5-6th": 2,
      "7-8th": 11,
      "9-12th": 51,
      "13-16th": 47,
      "17-18th": 84,
      "19-20th": 0,
      "elim_wc": 0,
      "points_qual": 0,
      "reg_qual": 149,
      "wc_qual": 0
    },
    "UALEIKUMNIHAO": {
      "1st": 0,
      "2nd": 0,
      "3rd": 1,
      "4th": 2,
      "5-6th": 13,
      "7-8th": 82,
      "9-12th": 501,
      "13-16th": 485,
      "17-18th": 787,
      "19-20th": 0,
      "elim_wc": 0,
      "points_qual": 0,
      "reg_qual": 1410,
      "wc_qual": 0
    },
    "cybercats": {
      "1st": 0,
      "2nd": 0,
      "3rd": 0,
      "4th": 0,
      "5-6th": 4,
      "7-8th": 31,
      "9-12th": 218,
      "13-16th": 216,
      "17-18th": 381,
      "19-20th": 0,
      "elim_wc": 0,
      "points_qual": 0,
      "reg_qual": 640,
      "wc_qual": 0
    },
    "Supernova": {
      "1st": 0,
      "2nd": 0,
      "3rd": 0,
      "4th": 0,
      "5-6th": 0,
      "7-8th": 0,
      "9-12th": 5,
      "13-16th": 5,
      "17-18th": 20,
      "19-20th": 0,
      "elim_wc": 0,
      "points_qual": 0,
      "reg_qual": 25,
      "wc_qual": 0
    },
    "na Div 2 team #1": {
      "1st": 0,
      "2nd": 0,
      "3rd": 0,
      "4th": 0,
      "5-6th": 1,
      "7-8th": 8,
      "9-12th": 85,
      "13-16th": 87,
      "17-18th": 468,
      "19-20th": 0,
      "elim_wc": 0,
      "points_qual": 0,
      "reg_qual": 562,
      "wc_qual": 0
    },
    "Poke Gaming": {
      "1st": 0,
      "2nd": 0,
      "3rd": 0,
      "4th": 0,
      "5-6th": 4,
      "7-8th": 21,
      "9-12th": 118,
      "13-16th": 118,
      "17-18th": 144,
      "19-20th": 0,
      "elim_wc": 0,
      "points_qual": 0,
      "reg_qual": 292,
      "wc_qual": 0
    },
    "Meteor Gaming": {
      "1st": 0,
      "2nd": 0,
      "3rd": 1,
      "4th": 0,
      "5-6th": 0,
      "7-8th": 10,
      "9-12th": 68,
      "13-16th": 63,
      "17-18th": 100,
      "19-20th": 0,
      "elim_wc": 0,
      "points_qual": 0,
      "reg_qual": 182,
      "wc_qual": 0
    },
    "eeu Div 2 team #2": {
      "1st": 0,
      "2nd": 0,
      "3rd": 0,
      "4th": 0,
      "5-6th": 0,
      "7-8th": 1,
      "9-12th": 3,
      "13-16th": 4,
      "17-18th": 31,
      "19-20th": 0,
      "elim_wc": 0,
      "points_qual": 0,
      "reg_qual": 35,
      "wc_qual": 0
    },
    "Myth Avenue Gaming": {
      "1st": 0,
      "2nd": 0,
      "3rd": 0,
      "4th": 0,
      "5-6th": 2,
      "7-8th": 10,
      "9-12th": 87,
      "13-16th": 89,
      "17-18th": 208,
      "19-20th": 0,
      "elim_wc": 0,
      "points_qual": 0,
      "reg_qual": 308,
      "wc_qual": 0
    },
    "PuckChamp": {
      "1st": 0,
      "2nd": 0,
      "3rd": 0,
      "4th": 0,
      "5-6th": 1,
      "7-8th": 2,
      "9-12th": 8,
      "13-16th": 9,
      "17-18th": 25,
      "19-20th": 0,
      "elim_wc": 0,
      "points_qual": 0,
      "reg_qual": 36,
      "wc_qual": 0
    },
    "Team Bright": {
      "1st": 0,
      "2nd": 0,
      "3rd": 0,
      "4th": 0,
      "5-6th": 2,
      "7-8th": 5,
      "9-12th": 41,
      "13-16th": 39,
      "17-18th": 84,
      "19-20th": 0,
      "elim_wc": 0,
      "points_qual": 0,
      "reg_qual": 134,
      "wc_qual": 0
    },
    "StoRm": {
      "1st": 0,
      "2nd": 0,
      "3rd": 0,
      "4th": 0,
      "5-6th": 0,
      "7-8th": 3,
      "9-12th": 37,
      "13-16th": 39,
      "17-18th": 114,
      "19-20th": 0,
      "elim_wc": 0,
      "points_qual": 0,
      "reg_qual": 154,
      "wc_qual": 0
    },
    "UD VESSUWAN": {
      "1st": 0,
      "2nd": 0,
      "3rd": 0,
      "4th": 0,
      "5-6th": 0,
      "7-8th": 5,
      "9-12th": 37,
      "13-16th": 37,
      "17-18th": 99,
      "19-20th": 0,
      "elim_wc": 0,
      "points_qual": 0,
      "reg_qual": 141,
      "wc_qual": 0
    },
    "Outsiders From CN": {
      "1st": 0,
      "2nd": 0,
      "3rd": 0,
      "4th": 0,
      "5-6th": 0,
      "7-8th": 7,
      "9-12th": 34,
      "13-16th": 35,
      "17-18th": 76,
      "19-20th": 0,
      "elim_wc": 0,
      "points_qual": 0,
      "reg_qual": 117,
      "wc_qual": 0
    },
    "sea Div 2 team #1": {
      "1st": 0,
      "2nd": 0,
      "3rd": 0,
      "4th": 0,
      "5-6th": 0,
      "7-8th": 1,
      "9-12th": 9,
      "13-16th": 9,
      "17-18th": 23,
      "19-20th": 0,
      "elim_wc": 0,
      "points_qual": 0,
      "reg_qual": 33,
      "wc_qual": 0
    },
    "The Cut": {
      "1st": 0,
      "2nd": 0,
      "3rd": 0,
      "4th": 0,
      "5-6th": 0,
      "7-8th": 1,
      "9-12th": 12,
      "13-16th": 13,
      "17-18th": 195,
      "19-20th": 0,
      "elim_wc": 0,
      "points_qual": 0,
      "reg_qual": 208,
      "wc_qual": 0
    },
    "sea Div 2 team #2": {
      "1st": 0,
      "2nd": 0,
      "3rd": 0,
      "4th": 0,
      "5-6th": 0,
      "7-8th": 0,
      "9-12th": 6,
      "13-16th": 5,
      "17-18th": 21,
      "19-20th": 0,
      "elim_wc": 0,
      "points_qual": 0,
      "reg_qual": 27,
      "wc_qual": 0
    },
    "Another NA Team": {
      "1st": 0,
      "2nd": 0,
      "3rd": 0,
      "4th": 0,
      "5-6th": 0,
      "7-8th": 0,
      "9-12th": 4,
      "13-16th": 4,
      "17-18th": 48,
      "19-20th": 0,
      "elim_wc": 0,
      "points_qual": 0,
      "reg_qual": 52,
      "wc_qual": 0
    },
    "CDUB Esports": {
      "1st": 0,
      "2nd": 0,
      "3rd": 0,
      "4th": 0,
      "5-6th": 0,
      "7-8th": 0,
      "9-12th": 11,
      "13-16th": 10,
      "17-18th": 74,
      "19-20th": 0,
      "elim_wc": 0,
      "points_qual": 0,
      "reg_qual": 85,
      "wc_qual": 0
    },
    "eeu Div 2 team #1": {
      "1st": 0,
      "2nd": 0,
      "3rd": 0,
      "4th": 0,
      "5-6th": 0,
      "7-8th": 0,
      "9-12th": 6,
      "13-16th": 5,
      "17-18th": 30,
      "19-20th": 0,
      "elim_wc": 0,
      "points_qual": 0,
      "reg_qual": 36,
      "wc_qual": 0
    },
    "cn Div 2 team #1": {
      "1st": 0,
      "2nd": 0,
      "3rd": 0,
      "4th": 0,
      "5-6th": 0,
      "7-8th": 0,
      "9-12th": 1,
      "13-16th": 1,
      "17-18th": 5,
      "19-20th": 0,
      "elim_wc": 0,
      "points_qual": 0,
      "reg_qual": 6,
      "wc_qual": 0
    },
    "NAVI Junior": {
      "1st": 0,
      "2nd": 0,
      "3rd": 0,
      "4th": 0,
      "5-6th": 0,
      "7-8th": 0,
      "9-12th": 10,
      "13-16th": 9,
      "17-18th": 30,
      "19-20th": 0,
      "elim_wc": 0,
      "points_qual": 0,
      "reg_qual": 40,
      "wc_qual": 0
    },
    "cn Div 2 team #2": {
      "1st": 0,
      "2nd": 0,
      "3rd": 0,
      "4th": 0,
      "5-6th": 0,
      "7-8th": 0,
      "9-12th": 0,
      "13-16th": 0,
      "17-18th": 6,
      "19-20th": 0,
      "elim_wc": 0,
      "points_qual": 0,
      "reg_qual": 6,
      "wc_qual": 0
    },
    "weu Div 2 team #1": {
      "1st": 0,
      "2nd": 0,
      "3rd": 0,
      "4th": 0,
      "5-6th": 0,
      "7-8th": 0,
      "9-12th": 0,
      "13-16th": 0,
      "17-18th": 3,
      "19-20th": 0,
      "elim_wc": 0,
      "points_qual": 0,
      "reg_qual": 3,
      "wc_qual": 0
    },
    "TiltedBoys": {
      "1st": 0,
      "2nd": 0,
      "3rd": 0,
      "4th": 0,
      "5-6th": 0,
      "7-8th": 0,
      "9-12th": 3,
      "13-16th": 3,
      "17-18th": 18,
      "19-20th": 0,
      "elim_wc": 0,
      "points_qual": 0,
      "reg_qual": 21,
      "wc_qual": 0
    },
    "cactus": {
      "1st": 0,
      "2nd": 0,
      "3rd": 0,
      "4th": 0,
      "5-6th": 0,
      "7-8th": 0,
      "9-12th": 0,
      "13-16th": 0,
      "17-18th": 2,
      "19-20th": 0,
      "elim_wc": 0,
      "points_qual": 0,
      "reg_qual": 2,
      "wc_qual": 0
    },
    "weu Div 2 team #2": {
      "1st": 0,
      "2nd": 0,
      "3rd": 0,
      "4th": 0,
      "5-6th": 0,
      "7-8th": 0,
      "9-12th": 0,
      "13-16th": 0,
      "17-18th": 1,
      "19-20th": 0,
      "elim_wc": 0,
      "points_qual": 0,
      "reg_qual": 1,
      "wc_qual": 0
    }
  },
  "updated": "05 June 2023 23:16:59",
  "min_threshold": 760,
  "max_threshold": 1160,
  "avg_threshold": 906.5106000003676
}